gluctool/__init__.py
gluctool/gluctool.py
gluctool-0.0.2.dist-info/licenses/LICENSE.txt
gluctool-0.0.2.dist-info/METADATA
gluctool-0.0.2.dist-info/WHEEL
gluctool-0.0.2.dist-info/entry_points.txt
gluctool-0.0.2.dist-info/top_level.txt
gluctool-0.0.2.dist-info/RECORD
