Metadata-Version: 2.4
Name: gluctool
Version: 0.0.2
Summary: Convert blood glucose levels between mmol/l and mg/dl.
Author-email: marshki <marshall@morethantomorrow.org>
License: The MIT License (MIT)
Classifier: Programming Language :: Python :: 3
Classifier: License :: OSI Approved :: MIT License
Classifier: Operating System :: OS Independent
Classifier: Topic :: Utilities
Requires-Python: >=3.9
License-File: LICENSE.txt
Dynamic: license-file
